khemiri/__init__.py
khemiri/fct_GCP.py
khemiri/fct_ai.py
khemiri/fct_aws.py
khemiri/fct_browser.py
khemiri/fct_captcha.py
khemiri/fct_core.py
khemiri/fct_db.py
khemiri/fct_dropbox.py
khemiri/fct_email.py
khemiri/fct_firecrawl.py
khemiri/fct_google_drive.py
khemiri/fct_mongodb.py
khemiri/fct_request.py
khemiri/fct_sheet.py
khemiri/fct_sqlite3.py
khemiri-0.3.0.dist-info/METADATA
khemiri-0.3.0.dist-info/WHEEL
khemiri-0.3.0.dist-info/top_level.txt
khemiri-0.3.0.dist-info/RECORD
