Metadata-Version: 2.1
Name: khemiri
Version: 0.3.0
Summary: khemiri packages
Author: khemiri
Requires-Python: >=3.10
